omniValidator/__init__.py
omniValidator/core.py
omniValidator/utils.py
omniValidator/version.py
omniValidator/schemas/omni_batch_py/omni_batch_data/output/requirements.json
omniValidator/schemas/omni_batch_py/omni_batch_method/output/requirements.json
omniValidator/schemas/omni_batch_py/omni_batch_metric_py/output/requirements.json
omniValidator/schemas/omni_batch_py/omni_batch_processed/output/requirements.json
omniValidator/schemas/omni_clustering/omni_clustering_data/output/requirements.json
omniValidator/schemas/omni_clustering/omni_clustering_filter/output/requirements.json
omniValidator/schemas/omni_clustering/omni_clustering_method/output/requirements.json
omniValidator/schemas/omni_clustering/omni_clustering_metric/output/requirements.json
omniValidator-0.0.19.dist-info/LICENSE
omniValidator-0.0.19.dist-info/METADATA
omniValidator-0.0.19.dist-info/WHEEL
omniValidator-0.0.19.dist-info/top_level.txt
omniValidator-0.0.19.dist-info/RECORD
